flexiplex_filter/__init__.py
flexiplex_filter/main.py
flexiplex_filter-1.2.dist-info/METADATA
flexiplex_filter-1.2.dist-info/WHEEL
flexiplex_filter-1.2.dist-info/entry_points.txt
flexiplex_filter-1.2.dist-info/top_level.txt
flexiplex_filter-1.2.dist-info/RECORD
