Metadata-Version: 2.4
Name: flexiplex-filter
Version: 1.2
Summary: Filter barcodes from flexiplex by whitelist and inflection point
Author-email: "Oliver Cheng, Davidson Group" <cheng.o@wehi.edu.au>
License-Expression: MIT
Project-URL: Homepage, https://github.com/DavidsonGroup/flexiplex
Project-URL: Bug Tracker, https://github.com/DavidsonGroup/flexiplex/issues
Classifier: Programming Language :: Python :: 3
Classifier: Operating System :: OS Independent
Requires-Python: >=3.8.12
Requires-Dist: cachetools
Requires-Dist: requests
Requires-Dist: matplotlib
Requires-Dist: numpy
Requires-Dist: pandas
